whisper_transcriber/__init__.py
whisper_transcriber/audio_processing.py
whisper_transcriber/cli.py
whisper_transcriber/transcriber.py
whisper_transcriber/utils.py
whisper_transcriber-0.2.6.dist-info/METADATA
whisper_transcriber-0.2.6.dist-info/WHEEL
whisper_transcriber-0.2.6.dist-info/entry_points.txt
whisper_transcriber-0.2.6.dist-info/top_level.txt
whisper_transcriber-0.2.6.dist-info/RECORD
