Metadata-Version: 2.4
Name: whisper_transcriber
Version: 0.2.6
Summary: A library for transcribing audio files using Whisper models
Home-page: https://github.com/COILDOrg/whisper-transcriber
Author: Ranjan Shettigar
Author-email: theloko.dev@gmail.com
License: MIT
Classifier: Programming Language :: Python :: 3
Classifier: License :: OSI Approved :: MIT License
Classifier: Operating System :: OS Independent
Requires-Python: >=3.7
Requires-Dist: torch
Requires-Dist: numpy
Requires-Dist: tqdm
Requires-Dist: librosa
Requires-Dist: transformers
Requires-Dist: huggingface_hub
Requires-Dist: regex
Requires-Dist: pathlib
Requires-Dist: concurrent-log-handler
Requires-Dist: ffmpeg-python
Dynamic: author
Dynamic: author-email
Dynamic: classifier
Dynamic: description
Dynamic: description-content-type
Dynamic: home-page
Dynamic: license
Dynamic: requires-dist
Dynamic: requires-python
Dynamic: summary
